flask_oauthlib/__init__.py
flask_oauthlib/client.py
flask_oauthlib/utils.py
flask_oauthlib/contrib/__init__.py
flask_oauthlib/contrib/apps.py
flask_oauthlib/contrib/cache.py
flask_oauthlib/contrib/oauth2.py
flask_oauthlib/contrib/client/__init__.py
flask_oauthlib/contrib/client/application.py
flask_oauthlib/contrib/client/descriptor.py
flask_oauthlib/contrib/client/exceptions.py
flask_oauthlib/contrib/client/signals.py
flask_oauthlib/contrib/client/structure.py
flask_oauthlib/provider/__init__.py
flask_oauthlib/provider/oauth1.py
flask_oauthlib/provider/oauth2.py
Patreon_Flask_OAuthlib-0.9.6.dist-info/AUTHORS
Patreon_Flask_OAuthlib-0.9.6.dist-info/LICENSE
Patreon_Flask_OAuthlib-0.9.6.dist-info/METADATA
Patreon_Flask_OAuthlib-0.9.6.dist-info/WHEEL
Patreon_Flask_OAuthlib-0.9.6.dist-info/top_level.txt
Patreon_Flask_OAuthlib-0.9.6.dist-info/RECORD
